sentry_relay-1.1.4.dist-info/RECORD
sentry_relay-1.1.4.dist-info/METADATA
sentry_relay-1.1.4.dist-info/top_level.txt
sentry_relay-1.1.4.dist-info/WHEEL
sentry_relay/_lowlevel__ffi.py
sentry_relay/_compat.py
sentry_relay/utils.py
sentry_relay/exceptions.py
sentry_relay/__init__.py
sentry_relay/consts.py
sentry_relay/_lowlevel.py
sentry_relay/_lowlevel__lib.so
sentry_relay/auth.py
sentry_relay/processing.py
